ckanext/__init__.py
ckanext/pycharm_debugger/__init__.py
ckanext/pycharm_debugger/config_declaration.yaml
ckanext/pycharm_debugger/plugin.py
ckanext/pycharm_debugger/test/__init__.py
ckanext/pycharm_debugger/test/test_pycharm_debugger_plugin.py
ckanext_pycharm_debugger-0.0.1.dist-info/licenses/LICENSE
ckanext_pycharm_debugger-0.0.1.dist-info/METADATA
ckanext_pycharm_debugger-0.0.1.dist-info/WHEEL
ckanext_pycharm_debugger-0.0.1.dist-info/entry_points.txt
ckanext_pycharm_debugger-0.0.1.dist-info/top_level.txt
ckanext_pycharm_debugger-0.0.1.dist-info/RECORD
