Metadata-Version: 2.4
Name: ckanext-pycharm_debugger
Version: 0.0.1
Summary: CKAN extension to enable PyCharm remote debugging
Author-email: William Dutton <william.dutton@qld.gov.au>
Maintainer-email: William Dutton <william.dutton@qld.gov.au>
License: MIT
Project-URL: Homepage, https://github.com/duttonw/ckanext-pycharm-debugger
Keywords: CKAN,PyCharm,remote debugging,debugger,extension,plugin
Classifier: Development Status :: 4 - Beta
Classifier: License :: OSI Approved :: GNU Affero General Public License v3 or later (AGPLv3+)
Classifier: Programming Language :: Python :: 3.7
Classifier: Programming Language :: Python :: 3.8
Classifier: Programming Language :: Python :: 3.9
Classifier: Programming Language :: Python :: 3.10
Classifier: Programming Language :: Python :: 3.11
Classifier: Programming Language :: Python :: 3.12
Requires-Python: >=3.8
License-File: LICENSE
Requires-Dist: ckan
Provides-Extra: test
Requires-Dist: pytest-ckan; extra == "test"
Requires-Dist: junit2html==31.0.2; extra == "test"
Provides-Extra: pycharm2024
Requires-Dist: pydevd-pycharm==241.18034.82; extra == "pycharm2024"
Provides-Extra: pycharm2025
Requires-Dist: pydevd-pycharm==251.25410.122; extra == "pycharm2025"
Dynamic: license-file
